pygmssl/__init__.py
pygmssl/_gm.py
pygmssl/exceptions.py
pygmssl/py.typed
pygmssl/sm2.py
pygmssl/sm3.py
pygmssl/sm4.py
pygmssl-0.1.2.dist-info/LICENSE
pygmssl-0.1.2.dist-info/METADATA
pygmssl-0.1.2.dist-info/WHEEL
pygmssl-0.1.2.dist-info/RECORD
