Metadata-Version: 2.1
Name: pygmssl
Version: 0.1.2
Summary: A Python ctypes implementation of GmSSLv3.1.1
Home-page: https://github.com/j-z10/pygmssl
License: MIT
Keywords: 国密,GmSSL,gmssl,sm2,sm3,sm4
Author: Zhang Jie
Author-email: zhangj_10ujs@foxmail.com
Maintainer: Zhang Jie
Maintainer-email: zhangj_10ujs@foxmail.com
Requires-Python: >=3.11,<4.0
Classifier: Development Status :: 3 - Alpha
Classifier: License :: OSI Approved :: MIT License
Classifier: Operating System :: OS Independent
Classifier: Programming Language :: Python :: 3
Classifier: Programming Language :: Python :: 3.11
Classifier: Programming Language :: Python :: 3.12
Requires-Dist: pycryptodomex (>=3.20.0,<4.0.0)
